{
  "meta": {
    "mode": "gpipe",
    "num_requests": 5,
    "seed": 37,
    "batch_size": 8,
    "store_hashes": false,
    "output_file": "./data/sample/gpipe_baseline.json",
    "omp_num_threads": "1",
    "world_size": 8,
    "device": "cpu",
    "clock": "time.perf_counter (last rank)",
    "argv": [
      "/Users/andrei/Documents/Uni5/Masters/model-runner/tests/baseline.py",
      "gpipe",
      "-n",
      "5",
      "-b",
      "8",
      "-o",
      "./data/sample/gpipe_baseline.json"
    ]
  },
  "results": {
    "conv_next": {
      "batches": [
        {
          "seed": 37,
          "timing": {
            "start": 600306.509752625,
            "end": 600309.678456625
          }
        },
        {
          "seed": 38,
          "timing": {
            "start": 600309.678458416,
            "end": 600312.896215625
          }
        },
        {
          "seed": 39,
          "timing": {
            "start": 600312.896217791,
            "end": 600316.110373916
          }
        },
        {
          "seed": 40,
          "timing": {
            "start": 600316.110375208,
            "end": 600319.32213975
          }
        },
        {
          "seed": 41,
          "timing": {
            "start": 600319.322143375,
            "end": 600322.532705916
          }
        }
      ],
      "requests_per_second": 2.4964186859717503
    },
    "conv_next_base": {
      "batches": [
        {
          "seed": 37,
          "timing": {
            "start": 600329.621390125,
            "end": 600333.850573416
          }
        },
        {
          "seed": 38,
          "timing": {
            "start": 600333.850574625,
            "end": 600338.128634791
          }
        },
        {
          "seed": 39,
          "timing": {
            "start": 600338.128636,
            "end": 600342.378205166
          }
        },
        {
          "seed": 40,
          "timing": {
            "start": 600342.378206416,
            "end": 600346.64346675
          }
        },
        {
          "seed": 41,
          "timing": {
            "start": 600346.643467875,
            "end": 600350.8792905
          }
        }
      ],
      "requests_per_second": 1.881653375662225
    },
    "efficientnet_b6": {
      "batches": [
        {
          "seed": 37,
          "timing": {
            "start": 600354.317577666,
            "end": 600355.458874708
          }
        },
        {
          "seed": 38,
          "timing": {
            "start": 600355.458876,
            "end": 600356.575711916
          }
        },
        {
          "seed": 39,
          "timing": {
            "start": 600356.5757135,
            "end": 600357.685121791
          }
        },
        {
          "seed": 40,
          "timing": {
            "start": 600357.685122875,
            "end": 600358.883345708
          }
        },
        {
          "seed": 41,
          "timing": {
            "start": 600358.883346833,
            "end": 600359.935078791
          }
        }
      ],
      "requests_per_second": 7.120603825459132
    },
    "regnet_x_16gf": {
      "batches": [
        {
          "seed": 37,
          "timing": {
            "start": 600361.354838166,
            "end": 600361.608235833
          }
        },
        {
          "seed": 38,
          "timing": {
            "start": 600361.608237166,
            "end": 600361.870938958
          }
        },
        {
          "seed": 39,
          "timing": {
            "start": 600361.870940666,
            "end": 600362.132302833
          }
        },
        {
          "seed": 40,
          "timing": {
            "start": 600362.132304291,
            "end": 600362.39502425
          }
        },
        {
          "seed": 41,
          "timing": {
            "start": 600362.395025541,
            "end": 600362.673346208
          }
        }
      ],
      "requests_per_second": 30.337319704301457
    }
  }
}